<annotation>
	<folder>o(ও)</folder>
	<filename>20180928_115242.jpg</filename>
	<path>C:\Users\ismi7\Downloads\BdSLImset-master\BdSLImset-master\o(ও)\20180928_115242.jpg</path>
	<source>
		<database>Unknown</database>
	</source>
	<size>
		<width>336</width>
		<height>448</height>
		<depth>3</depth>
	</size>
	<segmented>0</segmented>
	<object>
		<name>o</name>
		<pose>Unspecified</pose>
		<truncated>0</truncated>
		<difficult>0</difficult>
		<bndbox>
			<xmin>96</xmin>
			<ymin>164</ymin>
			<xmax>240</xmax>
			<ymax>308</ymax>
		</bndbox>
	</object>
</annotation>
